useshortcut/__init__.py
useshortcut/client.py
useshortcut/models.py
useshortcut-0.0.8.dist-info/licenses/LICENSE
useshortcut-0.0.8.dist-info/METADATA
useshortcut-0.0.8.dist-info/WHEEL
useshortcut-0.0.8.dist-info/top_level.txt
useshortcut-0.0.8.dist-info/RECORD
